dockerfile_generator/__init__.py
dockerfile_generator/main.py
dockerfile_generator/configs/alpine.json
dockerfile_generator/configs/debian.json
dockerfile_generator/configs/ubuntu.json
dockerfile_generator/configs/ubuntu_gcc.json
dockerfile_generator/templates/Dockerfile.jinja
dockerfile_generator/templates/build_stage_templates/alpine/rc/Dockerfile_plan9_build_stage.jinja
dockerfile_generator/templates/build_stage_templates/debian/heirloom/Dockerfile_heirloom_build_stage.jinja
dockerfile_generator/templates/command_templates/alpine-apk-testing.jinja
dockerfile_generator/templates/command_templates/apk.jinja
dockerfile_generator/templates/command_templates/apt-get.jinja
dockerfile_generator/templates/macros/build_stages.jinja
dockerfile_generator/templates/macros/commands.jinja
dockerfile_generator/templates/macros/image_and_tag.jinja
dockerfile_generator/templates/macros/labels.jinja
dockerfile_generator/templates/macros/versioned_param_list.jinja
dockerfile_generator-1.2.3.dist-info/METADATA
dockerfile_generator-1.2.3.dist-info/WHEEL
dockerfile_generator-1.2.3.dist-info/entry_points.txt
dockerfile_generator-1.2.3.dist-info/licenses/LICENSE
dockerfile_generator-1.2.3.dist-info/RECORD
