Metadata-Version: 2.1
Name: dockerfile_generator
Version: 1.2.3
Summary: Jinja 2 templates (with example config files) to generate Dockerfiles.
Project-URL: Homepage, https://github.com/JamesParrott/Dockerfile_generator
Project-URL: Bug Tracker, https://github.com/JamesParrott/Dockerfile_generator/issues
Author-email: James Parrott <james.parrott@proton.me>
License: Copyright 2023 James Parrott
License-File: LICENSE
Classifier: Operating System :: OS Independent
Classifier: Programming Language :: Python :: 3.7
Classifier: Programming Language :: Python :: 3.8
Classifier: Programming Language :: Python :: 3.9
Classifier: Programming Language :: Python :: 3.10
Classifier: Programming Language :: Python :: 3.11
Classifier: Programming Language :: Python :: 3.12
Requires-Python: >=3.7
Requires-Dist: jinja2
Provides-Extra: testing
Requires-Dist: pytest>=7.4; extra == 'testing'
